easy_vision/__init__.py
easy_vision-0.1.0.dist-info/METADATA
easy_vision-0.1.0.dist-info/WHEEL
easy_vision-0.1.0.dist-info/top_level.txt
easy_vision-0.1.0.dist-info/RECORD
