Metadata-Version: 2.1
Name: easy-vision
Version: 0.1.0
Summary: An framework for deep learning in vision, including image classification, object detection, semantic segmentation and ocr
Home-page: UNKNOWN
Author: Wenmengzhou
Author-email: wenmeng.zwm@alibaba-inc.com
License: UNKNOWN
Platform: UNKNOWN
